{
  "generated_at_utc": "2025-12-21T06:40:33Z",
  "watchlist": [
    "spy.us",
    "qqq.us",
    "iwm.us",
    "xlk.us",
    "xlf.us",
    "xle.us",
    "xlv.us",
    "xly.us",
    "xlb.us",
    "xli.us",
    "xlp.us",
    "xlu.us",
    "xlc.us",
    "aapl.us",
    "msft.us",
    "nvda.us",
    "amzn.us",
    "goog.us",
    "meta.us",
    "tsla.us",
    "amd.us",
    "avgo.us"
  ],
  "market_bias": {
    "score": 4,
    "bias": "bullish",
    "spy_close": 680.59,
    "spy_sma200": 622.44,
    "ema20_gt_ema50": true,
    "rsi14": 52.55,
    "roc20_pct": 4.3
  },
  "ideas": [
    {
      "symbol": "XLU.US",
      "plan": {
        "strategy": "TrendPullbackShort",
        "active": true,
        "entry": 42.55,
        "stop": 46.33,
        "target": 35.74,
        "rr": 1.8,
        "reason": "Downtrend, breakdown of prior low.",
        "direction": "bearish",
        "horizon": "short"
      }
    },
    {
      "symbol": "XLB.US",
      "plan": {
        "strategy": "TrendPullbackShort",
        "active": true,
        "entry": 45.04,
        "stop": 48.87,
        "target": 38.14,
        "rr": 1.8,
        "reason": "Downtrend, breakdown of prior low.",
        "direction": "bearish",
        "horizon": "short"
      }
    },
    {
      "symbol": "XLE.US",
      "plan": {
        "strategy": "TrendPullbackShort",
        "active": true,
        "entry": 43.98,
        "stop": 48.15,
        "target": 36.46,
        "rr": 1.8,
        "reason": "Downtrend, breakdown of prior low.",
        "direction": "bearish",
        "horizon": "short"
      }
    },
    {
      "symbol": "XLY.US",
      "plan": {
        "strategy": "TrendPullbackShort",
        "active": true,
        "entry": 121.69,
        "stop": 131.98,
        "target": 103.17,
        "rr": 1.8,
        "reason": "Downtrend, breakdown of prior low.",
        "direction": "bearish",
        "horizon": "short"
      }
    },
    {
      "symbol": "XLK.US",
      "plan": {
        "strategy": "TrendPullbackShort",
        "active": true,
        "entry": 142.52,
        "stop": 155.67,
        "target": 118.85,
        "rr": 1.8,
        "reason": "Downtrend, breakdown of prior low.",
        "direction": "bearish",
        "horizon": "short"
      }
    },
    {
      "symbol": "XLF.US",
      "plan": {
        "strategy": "TrendPullbackLong",
        "active": true,
        "entry": 55.07,
        "stop": 54.46,
        "target": 56.17,
        "rr": 1.8,
        "reason": "Uptrend, breakout of prior high.",
        "direction": "bullish",
        "horizon": "short"
      }
    },
    {
      "symbol": "TSLA.US",
      "plan": {
        "strategy": "TrendPullbackLong",
        "active": true,
        "entry": 490.54,
        "stop": 472.76,
        "target": 522.54,
        "rr": 1.8,
        "reason": "Uptrend, breakout of prior high.",
        "direction": "bullish",
        "horizon": "short"
      }
    },
    {
      "symbol": "XLV.US",
      "plan": {
        "strategy": "TrendPullbackLong",
        "active": true,
        "entry": 155.82,
        "stop": 153.92,
        "target": 159.23,
        "rr": 1.8,
        "reason": "Uptrend, breakout of prior high.",
        "direction": "bullish",
        "horizon": "short"
      }
    },
    {
      "symbol": "XLC.US",
      "plan": {
        "strategy": "TrendPullbackLong",
        "active": true,
        "entry": 117.23,
        "stop": 116.09,
        "target": 119.27,
        "rr": 1.8,
        "reason": "Uptrend, breakout of prior high.",
        "direction": "bullish",
        "horizon": "short"
      }
    },
    {
      "symbol": "XLI.US",
      "plan": {
        "strategy": "TrendPullbackLong",
        "active": true,
        "entry": 156.17,
        "stop": 154.27,
        "target": 159.58,
        "rr": 1.8,
        "reason": "Uptrend, breakout of prior high.",
        "direction": "bullish",
        "horizon": "short"
      }
    },
    {
      "symbol": "IWM.US",
      "plan": {
        "strategy": "TrendPullbackLong",
        "active": true,
        "entry": 251.45,
        "stop": 247.65,
        "target": 258.3,
        "rr": 1.8,
        "reason": "Uptrend, breakout of prior high.",
        "direction": "bullish",
        "horizon": "short"
      }
    },
    {
      "symbol": "XLP.US",
      "plan": {
        "strategy": "TrendPullbackLong",
        "active": true,
        "entry": 79.2,
        "stop": 78.49,
        "target": 80.5,
        "rr": 1.8,
        "reason": "Uptrend, breakout of prior high.",
        "direction": "bullish",
        "horizon": "short"
      }
    },
    {
      "symbol": "GOOG.US",
      "plan": {
        "strategy": "WeeklyTrendLong",
        "active": true,
        "entry": 308.61,
        "stop": 271.4,
        "target": 383.03,
        "rr": 2.0,
        "reason": "Weekly uptrend (close>SMA40, EMA10>EMA30, RSIw>55). Position trade.",
        "direction": "bullish",
        "horizon": "long"
      }
    },
    {
      "symbol": "TSLA.US",
      "plan": {
        "strategy": "WeeklyTrendLong",
        "active": true,
        "entry": 481.2,
        "stop": 400.57,
        "target": 642.46,
        "rr": 2.0,
        "reason": "Weekly uptrend (close>SMA40, EMA10>EMA30, RSIw>55). Position trade.",
        "direction": "bullish",
        "horizon": "long"
      }
    },
    {
      "symbol": "AMD.US",
      "plan": {
        "strategy": "WeeklyTrendLong",
        "active": true,
        "entry": 213.43,
        "stop": 160.02,
        "target": 320.25,
        "rr": 2.0,
        "reason": "Weekly uptrend (close>SMA40, EMA10>EMA30, RSIw>55). Position trade.",
        "direction": "bullish",
        "horizon": "long"
      }
    },
    {
      "symbol": "AAPL.US",
      "plan": {
        "strategy": "WeeklyTrendLong",
        "active": true,
        "entry": 273.67,
        "stop": 252.29,
        "target": 316.44,
        "rr": 2.0,
        "reason": "Weekly uptrend (close>SMA40, EMA10>EMA30, RSIw>55). Position trade.",
        "direction": "bullish",
        "horizon": "long"
      }
    },
    {
      "symbol": "XLV.US",
      "plan": {
        "strategy": "WeeklyTrendLong",
        "active": true,
        "entry": 154.94,
        "stop": 145.74,
        "target": 173.33,
        "rr": 2.0,
        "reason": "Weekly uptrend (close>SMA40, EMA10>EMA30, RSIw>55). Position trade.",
        "direction": "bullish",
        "horizon": "long"
      }
    },
    {
      "symbol": "IWM.US",
      "plan": {
        "strategy": "WeeklyTrendLong",
        "active": true,
        "entry": 250.79,
        "stop": 230.34,
        "target": 291.69,
        "rr": 2.0,
        "reason": "Weekly uptrend (close>SMA40, EMA10>EMA30, RSIw>55). Position trade.",
        "direction": "bullish",
        "horizon": "long"
      }
    },
    {
      "symbol": "SPY.US",
      "plan": {
        "strategy": "WeeklyTrendLong",
        "active": true,
        "entry": 680.59,
        "stop": 647.67,
        "target": 746.43,
        "rr": 2.0,
        "reason": "Weekly uptrend (close>SMA40, EMA10>EMA30, RSIw>55). Position trade.",
        "direction": "bullish",
        "horizon": "long"
      }
    },
    {
      "symbol": "QQQ.US",
      "plan": {
        "strategy": "WeeklyTrendLong",
        "active": true,
        "entry": 617.05,
        "stop": 573.81,
        "target": 703.54,
        "rr": 2.0,
        "reason": "Weekly uptrend (close>SMA40, EMA10>EMA30, RSIw>55). Position trade.",
        "direction": "bullish",
        "horizon": "long"
      }
    }
  ],
  "disclaimer": "Educational use only. Not financial advice. Data provided as-is from public sources."
}